test_python/__init__.py
test_python/_version.py
test_python/main.py
raul_python_test-0.0.9.dist-info/METADATA
raul_python_test-0.0.9.dist-info/WHEEL
raul_python_test-0.0.9.dist-info/entry_points.txt
raul_python_test-0.0.9.dist-info/top_level.txt
raul_python_test-0.0.9.dist-info/RECORD
