Metadata-Version: 2.4
Name: raul_python_test
Version: 0.0.9
Summary: Raul's Python Test project
Author-email: Raul Viera-Mercado <vieramercado1@llnl.gov>
License-Expression: MIT
Project-URL: Homepage, https://github.com/vieramercado/test-python
Project-URL: Repository, https://github.com/vieramercado/test-python.git
Keywords: test,alpha
Classifier: Programming Language :: Python :: 3
Classifier: Operating System :: OS Independent
Classifier: Programming Language :: Python :: 3 :: Only
Classifier: Environment :: Console
Requires-Python: >=3.11
Provides-Extra: dev
Requires-Dist: build; extra == "dev"
Requires-Dist: virtualenv; extra == "dev"
Requires-Dist: setuptools-scm; extra == "dev"
Requires-Dist: twine; extra == "dev"
